bdacode/__init__.py
bdacode/answer.py
bdacode-0.1.1.dist-info/METADATA
bdacode-0.1.1.dist-info/WHEEL
bdacode-0.1.1.dist-info/top_level.txt
bdacode-0.1.1.dist-info/RECORD
