Metadata-Version: 2.1
Name: bdacode
Version: 0.1.1
Summary: A Python package for BDA answers.
Author: Naveen Sakthi
Author-email: naveendgp@gmail.com
Classifier: Programming Language :: Python :: 3
Classifier: License :: OSI Approved :: MIT License
Classifier: Operating System :: OS Independent
Requires-Python: >=3.6
Requires-Dist: numpy
